apple_wallet/__init__.py
apple_wallet/models.py
apple_wallet/settings.py
apple_wallet-0.2.0.dist-info/METADATA
apple_wallet-0.2.0.dist-info/WHEEL
apple_wallet-0.2.0.dist-info/RECORD
