Metadata-Version: 2.1
Name: apple-wallet
Version: 0.2.0
Summary: A simple library to create Apple passes compatible with Wallet
License: MIT
Keywords: apple pass,apple wallet
Author: Borja Toron-Antons
Author-email: borja.toron@gmail.com
Requires-Python: >=3.12,<4.0
Classifier: Development Status :: 4 - Beta
Classifier: Intended Audience :: Developers
Classifier: License :: OSI Approved :: MIT License
Classifier: Natural Language :: English
Classifier: Operating System :: OS Independent
Classifier: Programming Language :: Python :: 3
Classifier: Programming Language :: Python :: 3.12
Classifier: Programming Language :: Python :: 3.13
Classifier: Programming Language :: Python :: 3.9
Requires-Dist: cryptography (>=43.0.1,<44.0.0)
Requires-Dist: pydantic (>=2.9.2,<3.0.0)
Requires-Dist: pydantic-settings (>=2.5.2,<3.0.0)
